{"sprites":[{"name":null,"x":0,"y":0,"width":16,"height":16,"textureId":"oryx-lofi-fantasy-creatures-8px-sprite0","ss":"oryx-lofi-fantasy-creatures-8px","descriptors":{"Demon":true},"id":"sprite0"},{"name":null,"x":16,"y":0,"width":16,"height":16,"textureId":"oryx-lofi-fantasy-creatures-8px-sprite1","ss":"oryx-lofi-fantasy-creatures-8px","descriptors":{"Demon":true},"id":"sprite1"},{"name":null,"x":32,"y":0,"width":16,"height":16,"textureId":"oryx-lofi-fantasy-creatures-8px-sprite2","ss":"oryx-lofi-fantasy-creatures-8px","descriptors":{"Troll":true},"id":"sprite2"},{"name":null,"x":48,"y":0,"width":16,"height":16,"textureId":"oryx-lofi-fantasy-creatures-8px-sprite3","ss":"oryx-lofi-fantasy-creatures-8px","descriptors":{"Dragon":true},"id":"sprite3"},{"name":null,"x":64,"y":0,"width":16,"height":16,"textureId":"oryx-lofi-fantasy-creatures-8px-sprite4","ss":"oryx-lofi-fantasy-creatures-8px","descriptors":{"Dragon":true},"id":"sprite4"},{"name":null,"x":80,"y":0,"width":16,"height":16,"textureId":"oryx-lofi-fantasy-creatures-8px-sprite5","ss":"oryx-lofi-fantasy-creatures-8px","descriptors":{"Dragon":true},"id":"sprite5"},{"name":null,"x":96,"y":0,"width":16,"height":16,"textureId":"oryx-lofi-fantasy-creatures-8px-sprite6","ss":"oryx-lofi-fantasy-creatures-8px","descriptors":{"Dragon":true},"id":"sprite6"},{"name":null,"x":112,"y":0,"width":16,"height":16,"textureId":"oryx-lofi-fantasy-creatures-8px-sprite7","ss":"oryx-lofi-fantasy-creatures-8px","descriptors":{"Dragon":true},"id":"sprite7"},{"name":null,"x":0,"y":16,"width":16,"height":16,"textureId":"oryx-lofi-fantasy-creatures-8px-sprite8","ss":"oryx-lofi-fantasy-creatures-8px","descriptors":{"Minotaur":true},"id":"sprite8"},{"name":null,"x":16,"y":16,"width":16,"height":16,"textureId":"oryx-lofi-fantasy-creatures-8px-sprite9","ss":"oryx-lofi-fantasy-creatures-8px","id":"sprite9"},{"name":null,"x":32,"y":16,"width":16,"height":16,"textureId":"oryx-lofi-fantasy-creatures-8px-sprite10","ss":"oryx-lofi-fantasy-creatures-8px","id":"sprite10"},{"name":null,"x":48,"y":16,"width":16,"height":16,"textureId":"oryx-lofi-fantasy-creatures-8px-sprite11","ss":"oryx-lofi-fantasy-creatures-8px","descriptors":{"Golem":true},"id":"sprite11"},{"name":null,"x":64,"y":16,"width":16,"height":16,"textureId":"oryx-lofi-fantasy-creatures-8px-sprite12","ss":"oryx-lofi-fantasy-creatures-8px","descriptors":{"Golem":true},"id":"sprite12"},{"name":null,"x":80,"y":16,"width":16,"height":16,"textureId":"oryx-lofi-fantasy-creatures-8px-sprite13","ss":"oryx-lofi-fantasy-creatures-8px","descriptors":{"Golem":true},"id":"sprite13"},{"name":null,"x":96,"y":16,"width":16,"height":16,"textureId":"oryx-lofi-fantasy-creatures-8px-sprite14","ss":"oryx-lofi-fantasy-creatures-8px","descriptors":{"Genie":true},"id":"sprite14"},{"name":null,"x":112,"y":16,"width":16,"height":16,"textureId":"oryx-lofi-fantasy-creatures-8px-sprite15","ss":"oryx-lofi-fantasy-creatures-8px","descriptors":{"Ent":true},"id":"sprite15"},{"name":null,"x":0,"y":32,"width":16,"height":16,"textureId":"oryx-lofi-fantasy-creatures-8px-sprite16","ss":"oryx-lofi-fantasy-creatures-8px","descriptors":{"Evil Eyeball":true},"id":"sprite16"},{"name":null,"x":16,"y":32,"width":16,"height":16,"textureId":"oryx-lofi-fantasy-creatures-8px-sprite17","ss":"oryx-lofi-fantasy-creatures-8px","id":"sprite17"},{"name":null,"x":32,"y":32,"width":16,"height":16,"textureId":"oryx-lofi-fantasy-creatures-8px-sprite18","ss":"oryx-lofi-fantasy-creatures-8px","descriptors":{"Possessed Object":true},"id":"sprite18"},{"name":null,"x":48,"y":32,"width":16,"height":16,"textureId":"oryx-lofi-fantasy-creatures-8px-sprite19","ss":"oryx-lofi-fantasy-creatures-8px","descriptors":{"Possessed Object":true},"id":"sprite19"},{"name":null,"x":64,"y":32,"width":16,"height":16,"textureId":"oryx-lofi-fantasy-creatures-8px-sprite20","ss":"oryx-lofi-fantasy-creatures-8px","descriptors":{"Demon":true},"id":"sprite20"},{"name":null,"x":80,"y":32,"width":16,"height":16,"textureId":"oryx-lofi-fantasy-creatures-8px-sprite21","ss":"oryx-lofi-fantasy-creatures-8px","id":"sprite21"},{"name":null,"x":96,"y":32,"width":16,"height":16,"textureId":"oryx-lofi-fantasy-creatures-8px-sprite22","ss":"oryx-lofi-fantasy-creatures-8px","id":"sprite22"},{"name":null,"x":112,"y":32,"width":16,"height":16,"textureId":"oryx-lofi-fantasy-creatures-8px-sprite23","ss":"oryx-lofi-fantasy-creatures-8px","descriptors":{"Ghost":true},"id":"sprite23"},{"name":null,"x":0,"y":48,"width":16,"height":16,"textureId":"oryx-lofi-fantasy-creatures-8px-sprite24","ss":"oryx-lofi-fantasy-creatures-8px","descriptors":{"Computer":true},"id":"sprite24"},{"name":null,"x":16,"y":48,"width":16,"height":16,"textureId":"oryx-lofi-fantasy-creatures-8px-sprite25","ss":"oryx-lofi-fantasy-creatures-8px","descriptors":{"Robot":true},"id":"sprite25"},{"name":null,"x":32,"y":48,"width":16,"height":16,"textureId":"oryx-lofi-fantasy-creatures-8px-sprite26","ss":"oryx-lofi-fantasy-creatures-8px","descriptors":{"Centaur":true},"id":"sprite26"}],"id":"oryx-lofi-fantasy-creatures-8px","imageUrl":"ss/oryx/lofi_fantasy_creatures.png","author":"oryx","serverImageUrl":"assets/images/ss/oryx/lofi_fantasy_creatures.png","tags":["monsters","fantasy"],"name":"Monsters ( Oryx )"}